Workbook
Name COEF: '表紙(工事)'!$N$4
Name OVERHEAD_RATE: '表紙(工事)'!$N$5
Name ROUND_UNIT: '表紙(工事)'!$N$6
Name WELFARE_RATE: '法定福利費内訳明細書'!$E$29
Name LABOR_DAY: '表紙(工事)'!$N$8
Name TARGET: '表紙(工事)'!$N$9

Sheet 表紙(工事)
A1: 御 見 積 書
J3: No. | M3: 【設定・内部用】（印刷範囲外）
J4: 46302 | M4: 提出係数（原価→定価ベース単価） | N4: 1.22
A5: 株式会社共栄店舗 | G5: 御中 | M5: 諸経費率（現場経費・運搬・雑材・工事諸経費） | N5: 0.22
M6: 出精値引き 丸め単位（目標額空欄時） | N6: 10000
A7: 金額 | B7: ="¥"&TEXT(K31,"#,##0")&"-" -> ¥1,850,000- | F7: （税別） | H7: 宮地機工株式会社 | M7: 法定福利費率（労務費比） | N7: =WELFARE_RATE -> 0.16375
M8: 労務原価日額（円/人工） | N8: 19000
A9: 上記の通り御見積申し上げます。 | H9: 代表取締役 濱本 義樹 | M9: 目標提出額（税別・空欄なら丸め）
A10: 何卒ご用命賜わりますようお願い申し上げます。 | M10: 参考：宮地機工 人工単価（定価ベース） | N10: 23225
H11: 〒722-0051 | M11: ※ 原価＝材料原価＋人工×N8。提出単価＝原価×N4（1.22で参考見積の人工単価23,225に一致）。目標提出額 N9 を入れると出精値引きで合わせる
A12: 工事名 | D12: 吉野家 呉海岸通店 新設工事 | H12: 広島県尾道市東尾道9-9
D13: 空調設備工事 | H13: TEL.0848-20-2121 | K13: FAX.0848-20-2126
A14: 施工場所 | D14: 広島県呉市海岸（国道31号沿い） | H14: 担当者 | J14: 濱本 義武
A15: 工事期限 | D15: 全体工期 2026年9月1日～2026年11月16日（空調設備工事は工程表による・天井配管 10月上旬予定）
A16: 御支払条件 | D16: 別途お打ち合わせ
A17: 有効期限 | D17: 発行後3ヶ月
A19: 項 目 | B19: 内 容 | G19: 数 量 | H19: 単位 | I19: 単 価 | K19: 金 額 | L19: 備 考 | M19: 内部集計（原価・粗利） | N19: 基準原価 | O19: 労務費(提出) | P19: 粗利 | Q19: 粗利率
B20: 【吉野家 呉海岸通店 新設工事 空調設備工事】
B21: ［工事範囲：機器吊込み・冷媒配管（ガス管保温20mm）・VPドレン・ドレン配管GW保温・室外機設置 空調機・吹出しパンカーは支給品］
A22: ① | B22: 機器吊込み・据付（空調機 支給品） | G22: 1 | H22: 式 | I22: =K22 -> 87350 | K22: ='内訳書(空調設備工事)'!H9 -> 87350 | L22: 内訳書 （1） | M22: ①機器吊込み・据付 | N22: ='内訳書(空調設備工事)'!O9 -> 71600 | O22: ='内訳書(空調設備工事)'!P9 -> 78812 | P22: =K22-N22 -> 15750 | Q22: =IF(K22=0,"",P22/K22) -> 0.1803091
A23: ② | B23: 冷媒配管（被覆銅管・ガス管保温20mm） | G23: 1 | H23: 式 | I23: =K23 -> 710310 | K23: ='内訳書(空調設備工事)'!H17 -> 710310 | L23: 内訳書 （2） | M23: ②冷媒配管 | N23: ='内訳書(空調設備工事)'!O17 -> 582100 | O23: ='内訳書(空調設備工事)'!P17 -> 345382 | P23: =K23-N23 -> 128210 | Q23: =IF(K23=0,"",P23/K23) -> 0.18049866
A24: ③ | B24: ドレン配管（硬質塩化ビニル管 VP） | G24: 1 | H24: 式 | I24: =K24 -> 77500 | K24: ='内訳書(空調設備工事)'!H24 -> 77500 | L24: 内訳書 （3） | M24: ③ドレン配管 | N24: ='内訳書(空調設備工事)'!O24 -> 63515 | O24: ='内訳書(空調設備工事)'!P24 -> 60267 | P24: =K24-N24 -> 13985 | Q24: =IF(K24=0,"",P24/K24) -> 0.18045161
A25: ④ | B25: ドレン配管保温（グラスウール） | G25: 1 | H25: 式 | I25: =K25 -> 51090 | K25: ='内訳書(空調設備工事)'!H29 -> 51090 | L25: 内訳書 （4） | M25: ④ドレン配管保温 | N25: ='内訳書(空調設備工事)'!O29 -> 41880 | O25: ='内訳書(空調設備工事)'!P29 -> 28280 | P25: =K25-N25 -> 9210 | Q25: =IF(K25=0,"",P25/K25) -> 0.18027011
A26: ⑤ | B26: 室外機設置（2段架台・基礎・防振ゴム共） | G26: 1 | H26: 式 | I26: =K26 -> 505320 | K26: ='内訳書(空調設備工事)'!H39 -> 505320 | L26: 内訳書 （5） | M26: ⑤室外機設置 | N26: ='内訳書(空調設備工事)'!O39 -> 414200 | O26: ='内訳書(空調設備工事)'!P39 -> 157624 | P26: =K26-N26 -> 91120 | Q26: =IF(K26=0,"",P26/K26) -> 0.18032138
A27: ⑥ | B27: 法定福利費（労務費に係る事業主負担分） | G27: 1 | H27: 式 | I27: =K27 -> 109768 | K27: ='法定福利費内訳明細書'!F29 -> 109768 | L27: 別紙明細書 | M27: ⑥法定福利費（原価＝提出値） | N27: =K27 -> 109768
A28: ⑦ | B28: 諸経費（現場経費・資材運搬・工事諸経費） | G28: 1 | H28: 式 | I28: =K28 -> 315000 | K28: =ROUND(SUM(K22:K26)*OVERHEAD_RATE,-3) -> 315000 | L28: ="①〜⑤計の"&TEXT(OVERHEAD_RATE,"0%") -> ①〜⑤計の22% | M28: ⑦諸経費（原価計上なし） | N28: 0
B30: 出精値引き | K30: =IF(TARGET="",FLOOR(SUM(K22:K28),ROUND_UNIT)-SUM(K22:K28),TARGET-SUM(K22:K28)) -> -6338 | L30: 端数調整 | M30: 出精値引き（原価なし・粗利から控除） | N30: 0 | P30: =K30 -> -6338
B31: 合 計 | K31: =SUM(K22:K30) -> 1850000 | L31: （税別） | M31: 合計（原価合計／粗利／粗利率） | N31: =SUM(N22:N30) -> 1283063 | O31: =SUM(O22:O30) -> 670365 | P31: =K31-N31 -> 566937 | Q31: =IF(K31=0,"",P31/K31) -> 0.30645243
A33: ※ | B33: 本見積は換気空調機器表（F-01）・空調設備図（F-02-1）・平面図（A-08）に基づき当社にて数量を拾い出して積算しております。実施数量との差異は別途精算とさせていただきます。 | M33: 粗利率別 参考提出額（税別・万円未満切上げ） | N33: 参考提出額 | O33: 必要提出係数
A34: ※ | B34: 本見積の工事範囲は「機器吊込み・冷媒配管（ガス管保温20mm）・VPドレン・ドレン配管GW保温・室外機設置」です。空調機（AC-1・AC-2・RAC の室内機・室外機・リモコン）および吹出しパンカーは支給品のため含みません（吊込み・据付費のみ計上）。 | M34: 0.1 | N34: =ROUNDUP($N$31/(1-M34),-4) -> 1430000 | O34: =IF(SUM($N$22:$N$26)=0,"",ROUND(($N$31/(1-M34)-$N$27-$K$28)/SUM($N$22:$N$26),3)) -> 0.853
A35: ※ | B35: 渡り操作配線・リモコン取付、試運転調整、AC-2 吹出しダクト・吹出しパンカー取付、換気設備、電源・接地等の電気工事、建築工事は含みません。 | M35: 0.15 | N35: =ROUNDUP($N$31/(1-M35),-4) -> 1510000 | O35: =IF(SUM($N$22:$N$26)=0,"",ROUND(($N$31/(1-M35)-$N$27-$K$28)/SUM($N$22:$N$26),3)) -> 0.925
A36: ※ | B36: 仮設（足場・高所作業車等）、揚重機（クレーン等）、産業廃棄物（支給品の梱包材を含む）の処分は元請様にてご手配・ご負担願います。 | M36: 0.2 | N36: =ROUNDUP($N$31/(1-M36),-4) -> 1610000 | O36: =IF(SUM($N$22:$N$26)=0,"",ROUND(($N$31/(1-M36)-$N$27-$K$28)/SUM($N$22:$N$26),3)) -> 1.005
A37: ※ | B37: 想定数量の項目は別紙「御見積条件」記載の前提にて計上しており、実数量確定後に精算させていただきます。 | M37: 0.25 | N37: =ROUNDUP($N$31/(1-M37),-4) -> 1720000 | O37: =IF(SUM($N$22:$N$26)=0,"",ROUND(($N$31/(1-M37)-$N$27-$K$28)/SUM($N$22:$N$26),3)) -> 1.096
A38: ※ | B38: 本見積書に記載なき事項については別途とさせて頂きます。工事に係る電気・水道は無償支給願います。 | M38: 0.3 | N38: =ROUNDUP($N$31/(1-M38),-4) -> 1840000 | O38: =IF(SUM($N$22:$N$26)=0,"",ROUND(($N$31/(1-M38)-$N$27-$K$28)/SUM($N$22:$N$26),3)) -> 1.2
A39: ※ | B39: 本見積金額には消費税は含まれておりません。有効期限内でも銅管・鋼材等の市況が著しく変動した場合は再見積をさせていただくことがあります。 | M39: ※ 必要提出係数は諸経費を現状額に固定した場合の目安
A40: ※ | B40: 詳細条件は別紙「御見積条件」をご参照ください。

Sheet 内訳書(空調設備工事)
A1: 内 訳 書 | J1: 原 価 内 訳 書（内部用・印刷範囲外）
A2: 工事名：吉野家 呉海岸通店 新設工事 空調設備工事 | I2: 内訳書 No.1
A3: 名 称 | C3: 規格・寸法 | E3: 数 量 | F3: 単位 | G3: 単 価 | H3: 金 額 | I3: 備 考 | J3: 材料原価 | K3: 人工/単位 | L3: 労務原価 | M3: 基準原価単価 | N3: 提出係数 | O3: 基準原価 | P3: 労務費(提出) | Q3: 数量根拠 | R3: 粗利 | S3: 粗利率 | T3: 参考定価ベース | U3: 当社/参考 | V3: 単価出典・メモ（内部）
A4: 空調設備工事（機器吊込み・冷媒配管（ガス管保温20mm）・VPドレン・ドレン配管GW保温・室外機設置）
A5: （1）機器吊込み・据付（空調機は支給品）
A6: AC-1 室内機 吊込み・据付 | C6: 天井カセット形 5HP SSRC140C 客席（吊ボルト・化粧パネル取付共） | E6: 2 | F6: 台 | G6: =IF(M6="","",ROUND(M6*N6,-1)) -> 23300 | H6: =IF(G6="","",ROUND(E6*G6,0)) -> 46600 | I6: 支給品の吊込み | J6: 2000 | K6: 0.9 | L6: =ROUND(K6*LABOR_DAY,0) -> 17100 | M6: =J6+L6 -> 19100 | N6: =COEF -> 1.22 | O6: =E6*M6 -> 38200 | P6: =ROUND(E6*L6*N6,0) -> 41724 | Q6: 図面カウント | R6: =IF(H6="","",H6-O6) -> 8400 | S6: =IF(OR(H6="",H6=0),"",R6/H6) -> 0.18025751 | T6: 21700 | U6: =IF(OR(T6="",T6=0),"",G6/T6) -> 1.0737327 | V6: 6330476-3 搬入据付 238,750/11台≒21,700/台。木造天井のため吊ボルト受け金物・吊ボルト4本分を材料に加算｜
A7: AC-2 室内機 吊込み・据付 | C7: 天井ビルトイン形 5HP SSRB140C 厨房（吊ボルト共） | E7: 1 | F7: 台 | G7: =IF(M7="","",ROUND(M7*N7,-1)) -> 30870 | H7: =IF(G7="","",ROUND(E7*G7,0)) -> 30870 | I7: 支給品の吊込み | J7: 2500 | K7: 1.2 | L7: =ROUND(K7*LABOR_DAY,0) -> 22800 | M7: =J7+L7 -> 25300 | N7: =COEF -> 1.22 | O7: =E7*M7 -> 25300 | P7: =ROUND(E7*L7*N7,0) -> 27816 | Q7: 図面カウント | R7: =IF(H7="","",H7-O7) -> 5570 | S7: =IF(OR(H7="",H7=0),"",R7/H7) -> 0.18043408 | T7: 27860 | U7: =IF(OR(T7="",T7=0),"",G7/T7) -> 1.1080402 | V7: 6330558 VRV 大形室内機 搬入据付 27,860/台 相当（ビルトイン 5HP 約50kg、吊ボルト・受け金物共）｜
A8: RAC 室内機 据付 | C8: 壁掛形 2.2kW 店長室（据付板共） | E8: 1 | F8: 台 | G8: =IF(M8="","",ROUND(M8*N8,-1)) -> 9880 | H8: =IF(G8="","",ROUND(E8*G8,0)) -> 9880 | I8: 支給品の据付 | J8: 500 | K8: 0.4 | L8: =ROUND(K8*LABOR_DAY,0) -> 7600 | M8: =J8+L8 -> 8100 | N8: =COEF -> 1.22 | O8: =E8*M8 -> 8100 | P8: =ROUND(E8*L8*N8,0) -> 9272 | Q8: 図面カウント | R8: =IF(H8="","",H8-O8) -> 1780 | S8: =IF(OR(H8="",H8=0),"",R8/H8) -> 0.18016194 | V8: 6330539 RA 搬入据付 12,500/組（室内外1組）の室内機分（据付板・アンカー共）｜
A9: 小 計 | H9: =SUM(H6:H8) -> 87350 | K9: =SUMPRODUCT(E6:E8,K6:K8) -> 3.4 | O9: =SUM(O6:O8) -> 71600 | P9: =SUM(P6:P8) -> 78812 | R9: =H9-O9 -> 15750 | S9: =IF(H9=0,"",R9/H9) -> 0.1803091
A10: （2）冷媒配管（被覆銅管・ガス管保温20mm）
A11: 冷媒配管 φ9.52／φ15.88 | C11: 被覆銅管 ガス管保温厚20mm 継手・支持金物共（AC-1・AC-2） | E11: 35 | F11: m | G11: =IF(M11="","",ROUND(M11*N11,-1)) -> 13740 | H11: =IF(G11="","",ROUND(E11*G11,0)) -> 480900 | I11: 図面実測＋想定（別紙） | J11: 6700 | K11: 0.24 | L11: =ROUND(K11*LABOR_DAY,0) -> 4560 | M11: =J11+L11 -> 11260 | N11: =COEF -> 1.22 | O11: =E11*M11 -> 394100 | P11: =ROUND(E11*L11*N11,0) -> 194712 | Q11: 実測+推測 | R11: =IF(H11="","",H11-O11) -> 86800 | S11: =IF(OR(H11="",H11=0),"",R11/H11) -> 0.18049491 | T11: 12556 | U11: =IF(OR(T11="",T11=0),"",G11/T11) -> 1.0942975 | V11: 6330476-3 / 6330344-1 9.52+15.88 4,025/m・4.6 m/人工（10t×2）に、ガス管保温20t（耐熱PEF）の材料差 600/m・人工 0.02/m を加算｜平面実測 26.77m（AC-1西 11.15・AC-1東 7.54・AC-2 8.08）＋立上り（架台下段 2.2m×2・上段 0.9m×1）＋機器接続 0.3m×3＋余長 0.5m×3 ＝ 34.47m
A12: 冷媒配管 φ6.35／φ9.52 | C12: 被覆銅管 ガス管保温厚20mm 継手・支持金物共（RAC） | E12: 10 | F12: m | G12: =IF(M12="","",ROUND(M12*N12,-1)) -> 8270 | H12: =IF(G12="","",ROUND(E12*G12,0)) -> 82700 | I12: 図面実測＋想定（別紙） | J12: 2600 | K12: 0.22 | L12: =ROUND(K12*LABOR_DAY,0) -> 4180 | M12: =J12+L12 -> 6780 | N12: =COEF -> 1.22 | O12: =E12*M12 -> 67800 | P12: =ROUND(E12*L12*N12,0) -> 50996 | Q12: 実測+推測 | R12: =IF(H12="","",H12-O12) -> 14900 | S12: =IF(OR(H12="",H12=0),"",R12/H12) -> 0.18016929 | T12: 7328 | U12: =IF(OR(T12="",T12=0),"",G12/T12) -> 1.128548 | V12: 6330539 2分3分 1,450/m想定・5 m/人工 に、ガス管保温20t の材料差 400/m・人工 0.02/m を加算｜平面実測 7.65m＋立上り（架台上段）0.9m＋店長室 立下り 0.6m＋余長 0.3m ＝ 9.45m
A13: 外部冷媒配管 化粧カバー | C13: 屋外用スリムダクト 継手・端末カバー共 | E13: 10 | F13: m | G13: =IF(M13="","",ROUND(M13*N13,-1)) -> 5470 | H13: =IF(G13="","",ROUND(E13*G13,0)) -> 54700 | I13: 図面実測＋想定（別紙） | J13: 2200 | K13: 0.12 | L13: =ROUND(K13*LABOR_DAY,0) -> 2280 | M13: =J13+L13 -> 4480 | N13: =COEF -> 1.22 | O13: =E13*M13 -> 44800 | P13: =ROUND(E13*L13*N13,0) -> 27816 | Q13: 実測+推測 | R13: =IF(H13="","",H13-O13) -> 9900 | S13: =IF(OR(H13="",H13=0),"",R13/H13) -> 0.1809872 | T13: 3516 | U13: =IF(OR(T13="",T13=0),"",G13/T13) -> 1.5557452 | V13: 屋外用スリムダクト（耐候樹脂）本体＋ウォールコーナー・エルボ・端末カバー等の継手を m 当りに按分。参考は配管保温工事費 1,194/m（6330476-3）｜屋外の平面部 3.81m（4系統 実測）＋室外機→外壁貫通の立上り（下段 2.2m×2・上段 0.9m×2）＝ 10.01m
A14: 外壁貫通処理 | C14: 穴明け・パテ・シーリング（木造外壁） | E14: 4 | F14: 箇所 | G14: =IF(M14="","",ROUND(M14*N14,-1)) -> 7630 | H14: =IF(G14="","",ROUND(E14*G14,0)) -> 30520 | J14: 1500 | K14: 0.25 | L14: =ROUND(K14*LABOR_DAY,0) -> 4750 | M14: =J14+L14 -> 6250 | N14: =COEF -> 1.22 | O14: =E14*M14 -> 25000 | P14: =ROUND(E14*L14*N14,0) -> 23180 | Q14: 図面カウント | R14: =IF(H14="","",H14-O14) -> 5520 | S14: =IF(OR(H14="",H14=0),"",R14/H14) -> 0.18086501 | V14: 外壁穴明け φ65〜75（木造・サイディング）・パテ埋め・シーリング（参考実績なし）｜
A15: 気密試験・真空引き | C15: パッケージエアコン（AC-1×2・AC-2） | E15: 3 | F15: 系統 | G15: =IF(M15="","",ROUND(M15*N15,-1)) -> 17570 | H15: =IF(G15="","",ROUND(E15*G15,0)) -> 52710 | J15: 3000 | K15: 0.6 | L15: =ROUND(K15*LABOR_DAY,0) -> 11400 | M15: =J15+L15 -> 14400 | N15: =COEF -> 1.22 | O15: =E15*M15 -> 43200 | P15: =ROUND(E15*L15*N15,0) -> 41724 | Q15: 図面カウント | R15: =IF(H15="","",H15-O15) -> 9510 | S15: =IF(OR(H15="",H15=0),"",R15/H15) -> 0.18042117 | T15: 20000 | U15: =IF(OR(T15="",T15=0),"",G15/T15) -> 0.8785 | V15: 気密テスト 15,000〜25,000/系統・真空引き 3,750〜5,640/系統（6330558/344-1/549）｜
A16: 気密試験・真空引き | C16: ルームエアコン（RAC） | E16: 1 | F16: 系統 | G16: =IF(M16="","",ROUND(M16*N16,-1)) -> 8780 | H16: =IF(G16="","",ROUND(E16*G16,0)) -> 8780 | J16: 1500 | K16: 0.3 | L16: =ROUND(K16*LABOR_DAY,0) -> 5700 | M16: =J16+L16 -> 7200 | N16: =COEF -> 1.22 | O16: =E16*M16 -> 7200 | P16: =ROUND(E16*L16*N16,0) -> 6954 | Q16: 図面カウント | R16: =IF(H16="","",H16-O16) -> 1580 | S16: =IF(OR(H16="",H16=0),"",R16/H16) -> 0.17995444 | T16: 7500 | U16: =IF(OR(T16="",T16=0),"",G16/T16) -> 1.1706667 | V16: RA 気密・真空引き（6330539 試運転 7,500/3台 等から想定）｜
A17: 小 計 | H17: =SUM(H11:H16) -> 710310 | K17: =SUMPRODUCT(E11:E16,K11:K16) -> 14.9 | O17: =SUM(O11:O16) -> 582100 | P17: =SUM(P11:P16) -> 345382 | R17: =H17-O17 -> 128210 | S17: =IF(H17=0,"",R17/H17) -> 0.18049866
A18: （3）ドレン配管（硬質塩化ビニル管 VP）
A19: ドレン管 VP25 | C19: 継手・支持金物共（各機器〜主管・RAC） | E19: 9 | F19: m | G19: =IF(M19="","",ROUND(M19*N19,-1)) -> 3130 | H19: =IF(G19="","",ROUND(E19*G19,0)) -> 28170 | I19: 図面実測＋想定（別紙） | J19: 475 | K19: 0.11 | L19: =ROUND(K19*LABOR_DAY,0) -> 2090 | M19: =J19+L19 -> 2565 | N19: =COEF -> 1.22 | O19: =E19*M19 -> 23085 | P19: =ROUND(E19*L19*N19,0) -> 22948 | Q19: 実測+推測 | R19: =IF(H19="","",H19-O19) -> 5085 | S19: =IF(OR(H19="",H19=0),"",R19/H19) -> 0.18051118 | T19: 3134 | U19: =IF(OR(T19="",T19=0),"",G19/T19) -> 0.99872368 | V19: 6330344-1/476-3/248-2 VP25 313/m、工費 2,497/m｜平面実測 5.20m（東主管 2.72・AC-2枝 1.28・西枝 0.76・RAC 0.44）＋ドレンアップ立上り 0.3m×3＋東カセット接続 0.3m＋RAC 立下り 1.9m ＝ 8.30m
A20: ドレン管 VP30 | C20: 継手・支持金物共（主管） | E20: 4 | F20: m | G20: =IF(M20="","",ROUND(M20*N20,-1)) -> 3540 | H20: =IF(G20="","",ROUND(E20*G20,0)) -> 14160 | I20: 図面実測数量 | J20: 620 | K20: 0.12 | L20: =ROUND(K20*LABOR_DAY,0) -> 2280 | M20: =J20+L20 -> 2900 | N20: =COEF -> 1.22 | O20: =E20*M20 -> 11600 | P20: =ROUND(E20*L20*N20,0) -> 11126 | Q20: 実測 | R20: =IF(H20="","",H20-O20) -> 2560 | S20: =IF(OR(H20="",H20=0),"",R20/H20) -> 0.18079096 | V20: VP25・VP40 の補間｜
A21: ドレン管 VP40 | C21: 継手・支持金物共（主管・立下り） | E21: 6 | F21: m | G21: =IF(M21="","",ROUND(M21*N21,-1)) -> 3940 | H21: =IF(G21="","",ROUND(E21*G21,0)) -> 23640 | I21: 図面実測＋想定（別紙） | J21: 760 | K21: 0.13 | L21: =ROUND(K21*LABOR_DAY,0) -> 2470 | M21: =J21+L21 -> 3230 | N21: =COEF -> 1.22 | O21: =E21*M21 -> 19380 | P21: =ROUND(E21*L21*N21,0) -> 18080 | Q21: 実測+推測 | R21: =IF(H21="","",H21-O21) -> 4260 | S21: =IF(OR(H21="",H21=0),"",R21/H21) -> 0.18020305 | V21: VP25 比例｜平面実測 3.29m＋天井内→接続立上り（H=150）への立下り 2.45m ＝ 5.74m
A22: ドレンホース用逆止弁 | C22: NDB-20-25（図示品） | E22: 1 | F22: 個 | G22: =IF(M22="","",ROUND(M22*N22,-1)) -> 5730 | H22: =IF(G22="","",ROUND(E22*G22,0)) -> 5730 | J22: 2800 | K22: 0.1 | L22: =ROUND(K22*LABOR_DAY,0) -> 1900 | M22: =J22+L22 -> 4700 | N22: =COEF -> 1.22 | O22: =E22*M22 -> 4700 | P22: =ROUND(E22*L22*N22,0) -> 2318 | Q22: 図面カウント | R22: =IF(H22="","",H22-O22) -> 1030 | S22: =IF(OR(H22="",H22=0),"",R22/H22) -> 0.17975567 | V22: ドレンホース用逆止弁 NDB-20-25（図示品番）材＋取付（市況）｜
A23: ドレン通水試験 | E23: 1 | F23: 式 | G23: =IF(M23="","",ROUND(M23*N23,-1)) -> 5800 | H23: =IF(G23="","",ROUND(E23*G23,0)) -> 5800 | J23: 0 | K23: 0.25 | L23: =ROUND(K23*LABOR_DAY,0) -> 4750 | M23: =J23+L23 -> 4750 | N23: =COEF -> 1.22 | O23: =E23*M23 -> 4750 | P23: =ROUND(E23*L23*N23,0) -> 5795 | Q23: － | R23: =IF(H23="","",H23-O23) -> 1050 | S23: =IF(OR(H23="",H23=0),"",R23/H23) -> 0.18103448 | V23: ドレン通水試験（0.25人工）｜
A24: 小 計 | H24: =SUM(H19:H23) -> 77500 | K24: =SUMPRODUCT(E19:E23,K19:K23) -> 2.6 | O24: =SUM(O19:O23) -> 63515 | P24: =SUM(P19:P23) -> 60267 | R24: =H24-O24 -> 13985 | S24: =IF(H24=0,"",R24/H24) -> 0.18045161
A25: （4）ドレン配管保温（グラスウール）
A26: ドレン管保温 25A | C26: GW保温筒 厚20mm ALGC仕上げ | E26: 9 | F26: m | G26: =IF(M26="","",ROUND(M26*N26,-1)) -> 2490 | H26: =IF(G26="","",ROUND(E26*G26,0)) -> 22410 | I26: 図面実測＋想定（別紙） | J26: 900 | K26: 0.06 | L26: =ROUND(K26*LABOR_DAY,0) -> 1140 | M26: =J26+L26 -> 2040 | N26: =COEF -> 1.22 | O26: =E26*M26 -> 18360 | P26: =ROUND(E26*L26*N26,0) -> 12517 | Q26: 実測+推測 | R26: =IF(H26="","",H26-O26) -> 4050 | S26: =IF(OR(H26="",H26=0),"",R26/H26) -> 0.18072289 | V26: GW保温筒20 ALGC 25A（参考実績なし・市況）｜ドレン管 VP25 と同長
A27: ドレン管保温 30A | C27: GW保温筒 厚20mm ALGC仕上げ | E27: 4 | F27: m | G27: =IF(M27="","",ROUND(M27*N27,-1)) -> 2730 | H27: =IF(G27="","",ROUND(E27*G27,0)) -> 10920 | I27: 図面実測数量 | J27: 1000 | K27: 0.065 | L27: =ROUND(K27*LABOR_DAY,0) -> 1235 | M27: =J27+L27 -> 2235 | N27: =COEF -> 1.22 | O27: =E27*M27 -> 8940 | P27: =ROUND(E27*L27*N27,0) -> 6027 | Q27: 実測 | R27: =IF(H27="","",H27-O27) -> 1980 | S27: =IF(OR(H27="",H27=0),"",R27/H27) -> 0.18131868 | V27: GW保温筒20 ALGC 30A（同上）｜
A28: ドレン管保温 40A | C28: GW保温筒 厚20mm ALGC仕上げ | E28: 6 | F28: m | G28: =IF(M28="","",ROUND(M28*N28,-1)) -> 2960 | H28: =IF(G28="","",ROUND(E28*G28,0)) -> 17760 | I28: 図面実測＋想定（別紙） | J28: 1100 | K28: 0.07 | L28: =ROUND(K28*LABOR_DAY,0) -> 1330 | M28: =J28+L28 -> 2430 | N28: =COEF -> 1.22 | O28: =E28*M28 -> 14580 | P28: =ROUND(E28*L28*N28,0) -> 9736 | Q28: 実測+推測 | R28: =IF(H28="","",H28-O28) -> 3180 | S28: =IF(OR(H28="",H28=0),"",R28/H28) -> 0.17905405 | V28: GW保温筒20 ALGC 40A（同上）｜ドレン管 VP40 と同長
A29: 小 計 | H29: =SUM(H26:H28) -> 51090 | K29: =SUMPRODUCT(E26:E28,K26:K28) -> 1.22 | O29: =SUM(O26:O28) -> 41880 | P29: =SUM(P26:P28) -> 28280 | R29: =H29-O29 -> 9210 | S29: =IF(H29=0,"",R29/H29) -> 0.18027011
A30: （5）室外機設置
A31: AC-1 室外機 据付 | C31: 5HP 架台下段（系統名表示共） | E31: 1 | F31: 台 | G31: =IF(M31="","",ROUND(M31*N31,-1)) -> 20370 | H31: =IF(G31="","",ROUND(E31*G31,0)) -> 20370 | I31: 支給品の据付 | J31: 1500 | K31: 0.8 | L31: =ROUND(K31*LABOR_DAY,0) -> 15200 | M31: =J31+L31 -> 16700 | N31: =COEF -> 1.22 | O31: =E31*M31 -> 16700 | P31: =ROUND(E31*L31*N31,0) -> 18544 | Q31: 図面カウント | R31: =IF(H31="","",H31-O31) -> 3670 | S31: =IF(OR(H31="",H31=0),"",R31/H31) -> 0.18016691 | T31: 21700 | U31: =IF(OR(T31="",T31=0),"",G31/T31) -> 0.93870968 | V31: 6330476-3 搬入据付 21,700/台（基礎・架台は別行）。防振ゴム取付・系統名表示共｜
A32: AC-1 室外機 据付 | C32: 5HP 架台上段（揚重・系統名表示共） | E32: 1 | F32: 台 | G32: =IF(M32="","",ROUND(M32*N32,-1)) -> 31960 | H32: =IF(G32="","",ROUND(E32*G32,0)) -> 31960 | I32: 支給品の据付 | J32: 1500 | K32: 1.3 | L32: =ROUND(K32*LABOR_DAY,0) -> 24700 | M32: =J32+L32 -> 26200 | N32: =COEF -> 1.22 | O32: =E32*M32 -> 26200 | P32: =ROUND(E32*L32*N32,0) -> 30134 | Q32: 図面カウント | R32: =IF(H32="","",H32-O32) -> 5760 | S32: =IF(OR(H32="",H32=0),"",R32/H32) -> 0.18022528 | T32: 21700 | U32: =IF(OR(T32="",T32=0),"",G32/T32) -> 1.4728111 | V32: 架台上段（H≒1.6m）への揚重（人力3名＋リフター）を人工に加算｜
A33: AC-2 室外機 据付 | C33: 5HP 架台下段（系統名表示共） | E33: 1 | F33: 台 | G33: =IF(M33="","",ROUND(M33*N33,-1)) -> 20370 | H33: =IF(G33="","",ROUND(E33*G33,0)) -> 20370 | I33: 支給品の据付 | J33: 1500 | K33: 0.8 | L33: =ROUND(K33*LABOR_DAY,0) -> 15200 | M33: =J33+L33 -> 16700 | N33: =COEF -> 1.22 | O33: =E33*M33 -> 16700 | P33: =ROUND(E33*L33*N33,0) -> 18544 | Q33: 図面カウント | R33: =IF(H33="","",H33-O33) -> 3670 | S33: =IF(OR(H33="",H33=0),"",R33/H33) -> 0.18016691 | T33: 21700 | U33: =IF(OR(T33="",T33=0),"",G33/T33) -> 0.93870968 | V33: 6330476-3 搬入据付 21,700/台（基礎・架台は別行）。防振ゴム取付・系統名表示共｜
A34: RAC 室外機 据付 | C34: 架台上段（揚重・系統名表示共） | E34: 1 | F34: 台 | G34: =IF(M34="","",ROUND(M34*N34,-1)) -> 12200 | H34: =IF(G34="","",ROUND(E34*G34,0)) -> 12200 | I34: 支給品の据付 | J34: 500 | K34: 0.5 | L34: =ROUND(K34*LABOR_DAY,0) -> 9500 | M34: =J34+L34 -> 10000 | N34: =COEF -> 1.22 | O34: =E34*M34 -> 10000 | P34: =ROUND(E34*L34*N34,0) -> 11590 | Q34: 図面カウント | R34: =IF(H34="","",H34-O34) -> 2200 | S34: =IF(OR(H34="",H34=0),"",R34/H34) -> 0.18032787 | V34: 6330539 RA 搬入据付 12,500/組（室内外1組）の室外機分＋架台上段への揚重｜
A35: 室外機架台 | C35: 鉄骨2段積み 溶融亜鉛メッキ（AC-1 上下段） | E35: 1 | F35: 基 | G35: =IF(M35="","",ROUND(M35*N35,-1)) -> 181780 | H35: =IF(G35="","",ROUND(E35*G35,0)) -> 181780 | J35: 130000 | K35: 1 | L35: =ROUND(K35*LABOR_DAY,0) -> 19000 | M35: =J35+L35 -> 149000 | N35: =COEF -> 1.22 | O35: =E35*M35 -> 149000 | P35: =ROUND(E35*L35*N35,0) -> 23180 | Q35: 図面カウント | R35: =IF(H35="","",H35-O35) -> 32780 | S35: =IF(OR(H35="",H35=0),"",R35/H35) -> 0.18032787 | V35: 鉄骨2段架台 溶融亜鉛メッキ 5HP×2用（ダイキン H1,430 対応の段間寸法）材＋組立・据付。既製品相当の想定（要メーカー見積）｜
A36: 室外機架台 | C36: 鉄骨2段積み 溶融亜鉛メッキ（AC-2・RAC） | E36: 1 | F36: 基 | G36: =IF(M36="","",ROUND(M36*N36,-1)) -> 157380 | H36: =IF(G36="","",ROUND(E36*G36,0)) -> 157380 | J36: 110000 | K36: 1 | L36: =ROUND(K36*LABOR_DAY,0) -> 19000 | M36: =J36+L36 -> 129000 | N36: =COEF -> 1.22 | O36: =E36*M36 -> 129000 | P36: =ROUND(E36*L36*N36,0) -> 23180 | Q36: 図面カウント | R36: =IF(H36="","",H36-O36) -> 28380 | S36: =IF(OR(H36="",H36=0),"",R36/H36) -> 0.18032787 | V36: 鉄骨2段架台 溶融亜鉛メッキ 5HP＋RA用 材＋組立・据付。既製品相当の想定（要メーカー見積）｜
A37: 架台基礎 | C37: コンクリート置基礎 4個／基・SUSアンカー | E37: 2 | F37: 基 | G37: =IF(M37="","",ROUND(M37*N37,-1)) -> 29890 | H37: =IF(G37="","",ROUND(E37*G37,0)) -> 59780 | I37: 想定数量（別紙条件書） | J37: 15000 | K37: 0.5 | L37: =ROUND(K37*LABOR_DAY,0) -> 9500 | M37: =J37+L37 -> 24500 | N37: =COEF -> 1.22 | O37: =E37*M37 -> 49000 | P37: =ROUND(E37*L37*N37,0) -> 23180 | Q37: 推測 | R37: =IF(H37="","",H37-O37) -> 10780 | S37: =IF(OR(H37="",H37=0),"",R37/H37) -> 0.18032787 | T37: 23200 | U37: =IF(OR(T37="",T37=0),"",G37/T37) -> 1.2883621 | V37: コンクリート置基礎 4個/基＋ステンレスアンカー。参考 基礎工事 5,800〜10,000/台（6330539/549/476-3）｜基礎形状の図示なし。架台1基につき置基礎4個を想定（外構土間に直接アンカー固定の場合は減額）
A38: 防振ゴム | C38: 室外機用（4個／台） | E38: 4 | F38: 台分 | G38: =IF(M38="","",ROUND(M38*N38,-1)) -> 5370 | H38: =IF(G38="","",ROUND(E38*G38,0)) -> 21480 | J38: 2500 | K38: 0.1 | L38: =ROUND(K38*LABOR_DAY,0) -> 1900 | M38: =J38+L38 -> 4400 | N38: =COEF -> 1.22 | O38: =E38*M38 -> 17600 | P38: =ROUND(E38*L38*N38,0) -> 9272 | Q38: 図面カウント | R38: =IF(H38="","",H38-O38) -> 3880 | S38: =IF(OR(H38="",H38=0),"",R38/H38) -> 0.18063315 | V38: 室外機用防振ゴム 4個/台（市況）｜
A39: 小 計 | H39: =SUM(H31:H38) -> 505320 | K39: =SUMPRODUCT(E31:E38,K31:K38) -> 6.8 | O39: =SUM(O31:O38) -> 414200 | P39: =SUM(P31:P38) -> 157624 | R39: =H39-O39 -> 91120 | S39: =IF(H39=0,"",R39/H39) -> 0.18032138
A41: 【合 計】 | H41: =H9+H17+H24+H29+H39 -> 1431570 | K41: =K9+K17+K24+K29+K39 -> 28.92 | O41: =O9+O17+O24+O29+O39 -> 1173295 | P41: =P9+P17+P24+P29+P39 -> 670365 | R41: =H41-O41 -> 258275 | S41: =IF(H41=0,"",R41/H41) -> 0.18041381

Sheet 法定福利費内訳明細書
B1: 法 定 福 利 費 内 訳 明 細 書
B2: ="（御見積書 No."&'表紙(工事)'!K3&" の添付資料）" -> （御見積書 No. の添付資料）
B4: 見積年月日 | C4: ='表紙(工事)'!J4 -> 46302 | F4: 見積No. | G4: =IF('表紙(工事)'!K3="","",'表紙(工事)'!K3)
B5: 発注者名 | C5: 株式会社共栄店舗 御中
B6: 工事名 | C6: 吉野家 呉海岸通店 新設工事 空調設備工事
B7: 施工場所 | C7: 広島県呉市海岸（国道31号沿い）
B8: 会社名 | C8: 宮地機工株式会社 | F8: 所在地 | G8: 広島県尾道市東尾道9-9
B10: 【1】 労務費の内訳（法定福利費の算定基礎）
B11: ※ 本見積の労務費は、内訳書各項目の材工共単価のうち労務費相当額（自社施工分）の合計です。空調機は支給品のため含みません。
B12: 項 目 | C12: 労務費（円） | E12: 摘 要
B13: ①機器吊込み・据付 | C13: ='内訳書(空調設備工事)'!P9 -> 78812 | E13: 内訳書 （1） 各項目の労務費相当額の合計
B14: ②冷媒配管 | C14: ='内訳書(空調設備工事)'!P17 -> 345382 | E14: 内訳書 （2） 各項目の労務費相当額の合計
B15: ③ドレン配管 | C15: ='内訳書(空調設備工事)'!P24 -> 60267 | E15: 内訳書 （3） 各項目の労務費相当額の合計
B16: ④ドレン配管保温 | C16: ='内訳書(空調設備工事)'!P29 -> 28280 | E16: 内訳書 （4） 各項目の労務費相当額の合計
B17: ⑤室外機設置 | C17: ='内訳書(空調設備工事)'!P39 -> 157624 | E17: 内訳書 （5） 各項目の労務費相当額の合計
B18: 労 務 費 合 計 | C18: =SUM(C13:C17) -> 670365 | E18: ← 法定福利費の算定基礎額
B20: 【2】 法定福利費の算定
B21: 計算式： 法定福利費 ＝ 労務費 × 事業主負担料率 （保険ごとに円未満切捨て）
B22: 保険の種類 | C22: 対象労務費（円） | E22: 事業主負担料率 | F22: 法定福利費（円） | G22: 算定根拠
B23: 健康保険料 | C23: =$C$18 -> 670365 | E23: 0.0489 | F23: =ROUNDDOWN(C23*E23,0) -> 32780 | G23: 健康保険料率 9.780%（協会けんぽ 広島県 令和8年度）×1/2（労使折半）
B24: 介護保険料 | C24: =$C$18 -> 670365 | E24: 0.0081 | F24: =ROUNDDOWN(C24*E24,0) -> 5429 | G24: 介護保険料率 1.620%（全国一律 令和8年度）×1/2（労使折半）
B25: 子ども・子育て支援金 | C25: =$C$18 -> 670365 | E25: 0.00115 | F25: =ROUNDDOWN(C25*E25,0) -> 770 | G25: 支援金率 0.230%（令和8年4月分〜）×1/2（労使折半）
B26: 厚生年金保険料 | C26: =$C$18 -> 670365 | E26: 0.0915 | F26: =ROUNDDOWN(C26*E26,0) -> 61338 | G26: 厚生年金保険料率 18.300%（平成29年9月以降固定）×1/2（労使折半）
B27: 雇用保険料 | C27: =$C$18 -> 670365 | E27: 0.0105 | F27: =ROUNDDOWN(C27*E27,0) -> 7038 | G27: 雇用保険料率（建設の事業）事業主負担分 1.050%
B28: 子ども・子育て拠出金 | C28: =$C$18 -> 670365 | E28: 0.0036 | F28: =ROUNDDOWN(C28*E28,0) -> 2413 | G28: 拠出金率 0.360%（事業主全額負担）
B29: 合 計 | E29: =SUM(E23:E28) -> 0.16375 | F29: =SUM(F23:F28) -> 109768
B31: ※ 料率は見積作成時点（令和8年度）の公表料率によります。料率が改定された場合は改定後の料率により精算させていただきます。
B32: ※ 法定福利費は御見積書の⑥に計上しています。

Sheet 御見積条件
A1: 御見積条件・注意事項
A2: 吉野家 呉海岸通店 新設工事 空調設備工事 御見積書 添付
A4: 【1】御見積条件・注意事項
A5: 1. | B5: 本見積は換気空調機器表 F-01（2025.05.25）・空調設備図 F-02-1（2026.05.25）・平面図 A-08（2026.07.29）に基づき当社にて拾い出した数量により積算しております。冷媒管・ドレン管の平面延長は空調設備図（1/50）から計測し、立上り・立下り・機器接続部は想定数量として計上しています（別紙【2】参照）。
A6: 2. | B6: 本見積の工事範囲は、ご指示の「機器吊込み・冷媒配管（ガス管保温20mm）・VPドレン・ドレン配管GW保温・室外機設置」です。空調設備図の特記で空調設備工事とされている項目のうち、渡り操作配線・リモコン取付、リモコン・スイッチ類の名称表示、試運転調整は本見積に含みません。必要な場合は別途お見積りいたします。
A7: 3. | B7: 空調機（AC-1 天井カセット形 SSRC140C×2台、AC-2 天井ビルトイン形 SSRB140C×1台、RAC 店長室用×1台、各リモコン）および吹出しパンカー PK-SB#10TK×4台は支給品のため含みません。本見積は空調機の搬入・吊込み・据付費のみを計上しています。
A8: 4. | B8: AC-2（天井ビルトイン形）から吹出しパンカーまでのダクト・パンカー取付、換気設備（換気扇・送風機・フード・ダクト類）は本見積に含みません。
A9: 5. | B9: 空調設備図の特記により、室外機の基礎・鉄骨架台（2段積み・溶融亜鉛メッキ防錆処理）・防振ゴムは「室外機設置」に計上しています。架台は既製品相当とし、ダイキン製室外機（H1,430mm）に対応する段間寸法・背面と建物壁面の隙間200mm以上を確保します。外構の土間コンクリートに直接アンカー固定できる場合は基礎を減額いたします。
A10: 6. | B10: 冷媒管は被覆銅管とし、ガス管は保温厚20mm（耐熱ポリエチレンフォーム）、液管はメーカー標準被覆としています。屋外露出部は特記により断熱材巻きの上、屋外用化粧カバー（スリムダクト）仕上げとして計上しています。
A11: 7. | B11: 冷媒の追加充填は、各系統の配管長（最長約14m）が支給機のチャージレス配管長以内と想定し計上していません。必要となった場合は実費にて精算させていただきます。
A12: 8. | B12: ドレン管は硬質塩化ビニル管（VP）とし、空調設備図の口径（25A・30A・40A）により計上しています。範囲は各機器から「空調機ドレン接続立上り（H=150）」までとし、以降は給排水工事です。図示のドレンホース用逆止弁 NDB-20-25 は本見積に計上しています。
A13: 9. | B13: ドレン管の保温はグラスウール保温筒 厚20mm・アルミガラスクロス（ALGC）仕上げとして全長に計上しています。厨房内の露出部をステンレスラッキング等とする場合は別途協議とさせていただきます。
A14: 10. | B14: 冷媒管の外壁貫通穴明け（4箇所）は本見積に計上しています。構造材の補強、天井・壁の開口および仕上げ補修、天井点検口は建築工事とし含みません。
A15: 11. | B15: 仮設（足場・高所作業車・仮設電気・水道等）および産業廃棄物（支給品の梱包材を含む）の処分費は元請様にてご負担願います（当社発生材は指定集積場所への分別搬出まで）。
A16: 12. | B16: 工期は工程表（吉野家呉海岸通店新設工事 工程表）に基づく通常の日中作業を前提としております。夜間・休日作業、工程変更や他工事との輻輳による手待ち、工期延長に伴う経費増は別途協議とさせていただきます。
... A18: 14. | B18: 本見積金額には消費税は含まれておりません。労務費に係る法定福利費（事業主負担分）は別紙「法定福利費内訳明細書」のとおり計上しています。
A20: 【2】想定数量（推測）項目の前提
A21: 図面に数量・経路の記載がなく当社にて想定した項目です。「図面実測＋想定」は平面延長を図面計測し、立上り等を想定加算したものです。実数量確定後に精算させていただきます。
A22: No. | B22: 内訳書 | C22: 項 目 | D22: 前提・想定内容 | F22: 数量（区分）
A23: 1 | B23: （2） | C23: 冷媒配管 φ9.52／φ15.88 被覆銅管 ガス管保温厚20mm 継手・支持金物共（AC-1・AC-2） | D23: 平面実測 26.77m（AC-1西 11.15・AC-1東 7.54・AC-2 8.08）＋立上り（架台下段 2.2m×2・上段 0.9m×1）＋機器接続 0.3m×3＋余長 0.5m×3 ＝ 34.47m | F23: 35 m（実測＋想定）
A24: 2 | B24: （2） | C24: 冷媒配管 φ6.35／φ9.52 被覆銅管 ガス管保温厚20mm 継手・支持金物共（RAC） | D24: 平面実測 7.65m＋立上り（架台上段）0.9m＋店長室 立下り 0.6m＋余長 0.3m ＝ 9.45m | F24: 10 m（実測＋想定）
A25: 3 | B25: （2） | C25: 外部冷媒配管 化粧カバー 屋外用スリムダクト 継手・端末カバー共 | D25: 屋外の平面部 3.81m（4系統 実測）＋室外機→外壁貫通の立上り（下段 2.2m×2・上段 0.9m×2）＝ 10.01m | F25: 10 m（実測＋想定）
A26: 4 | B26: （3） | C26: ドレン管 VP25 継手・支持金物共（各機器〜主管・RAC） | D26: 平面実測 5.20m（東主管 2.72・AC-2枝 1.28・西枝 0.76・RAC 0.44）＋ドレンアップ立上り 0.3m×3＋東カセット接続 0.3m＋RAC 立下り 1.9m ＝ 8.30m | F26: 9 m（実測＋想定）
A27: 5 | B27: （3） | C27: ドレン管 VP40 継手・支持金物共（主管・立下り） | D27: 平面実測 3.29m＋天井内→接続立上り（H=150）への立下り 2.45m ＝ 5.74m | F27: 6 m（実測＋想定）
A28: 6 | B28: （4） | C28: ドレン管保温 25A GW保温筒 厚20mm ALGC仕上げ | D28: ドレン管 VP25 と同長 | F28: 9 m（実測＋想定）
A29: 7 | B29: （4） | C29: ドレン管保温 40A GW保温筒 厚20mm ALGC仕上げ | D29: ドレン管 VP40 と同長 | F29: 6 m（実測＋想定）
A30: 8 | B30: （5） | C30: 架台基礎 コンクリート置基礎 4個／基・SUSアンカー | D30: 基礎形状の図示なし。架台1基につき置基礎4個を想定（外構土間に直接アンカー固定の場合は減額） | F30: 2 基（想定）
A32: 【3】図面読み取りに関する確認事項
A33: 1. | B33: 宛名は元請様を株式会社共栄店舗（工程表の作成者）と想定して記載しています。ご指定があれば修正します。
A34: 2. | B34: 工事名は工程表の「吉野家呉海岸通店新設工事」によりました（図面標題は「吉野家 呉海岸店 新設工事」）。施工場所は位置図（呉海岸）によります。地番をご教示ください。
A35: 3. | B35: 冷媒管・ドレン管は空調設備図 F-02-1 の配管線（R・D 記号）をベクトルデータから計測しています。立上り・立下りは室外機設置概要図（2段架台）と天井高（客席 CH2,600、厨房・店長室 CH2,500）から想定しています。
A36: 4. | B36: 室外機は室外機設置概要図により、架台①＝AC-1（下段）＋AC-1（上段）、架台②＝AC-2（下段）＋RAC（上段）の組合せとしています。
A37: 5. | B37: 特記の「天井内冷媒配管は厚20耐熱ポリスチレンフォーム断熱材巻き」は、冷媒管用の耐熱ポリエチレンフォーム保温材（厚20mm）と解釈しています。
A38: 6. | B38: 施工地域が「北日本吉野家・関東営業本部」以外のため、支給機はダイキン SSRC140C・SSRB140C（モリタニ・ダイキン手配）を前提としています。
A39: 7. | B39: ドレン接続立上り（H=150）の立上り管および以降の排水管は給排水工事と解釈しています。

Sheet 数量拾い根拠(内部)
A1: 数量拾い根拠（内部用） ※計測方法: 空調設備図 F-02-1（A3 1/50）のベクトル線分（黒・線幅0.72pt）を連結し系統別に延長を集計（data/takeoff_f02.py）。「実測」=図面線分の平面延長、「想定」=立上り・立下り等の図面に無い部分
A2: 縮尺確認: 通り芯 Y6-Y5 910mm＝51.6pt、Y5-Y4 1,820mm＝103.3pt → 1pt＝17.64mm。拾い根拠画像: takeoff_F02_冷媒ドレン.png
A4: 1. 冷媒配管 系統別（空調設備図 F-02-1 1/50 実測＋想定）
A5: 系統 | B5: 管径 | C5: 平面実測(m) | D5: 想定加算(m) | E5: 合計(m) | F5: 想定内容
A6: AC-1（客席西 天井カセット） | B6: φ9.52/15.88 | C6: 11.15 | D6: 3 | E6: 14.15 | F6: 架台下段 立上り 2.2m・機器接続 0.3m・余長 0.5m
A7: AC-1（客席東 天井カセット） | B7: φ9.52/15.88 | C7: 7.54 | D7: 1.7 | E7: 9.24 | F7: 架台上段 立上り 0.9m・機器接続 0.3m・余長 0.5m
A8: AC-2（厨房 天井ビルトイン） | B8: φ9.52/15.88 | C8: 8.08 | D8: 3 | E8: 11.08 | F8: 架台下段 立上り 2.2m・機器接続 0.3m・余長 0.5m
A9: RAC（店長室 壁掛） | B9: φ6.35/9.52 | C9: 7.65 | D9: 1.8 | E9: 9.45 | F9: 架台上段 立上り 0.9m・壁掛機への立下り 0.6m・余長 0.3m
A10: 合計 → 内訳書 | C10: 34.42 | D10: 9.5 | E10: 43.92 | F10: φ9.52/15.88 35m・φ6.35/9.52 10m（切上げ）
A12: 2. 外部冷媒配管 化粧カバー
A13: 系統 | B13: 屋外平面(m) | C13: 立上り(m) | D13: 合計(m) | F13: 備考
A14: AC-1（下段） | B14: 0.65 | C14: 2.2 | D14: 2.85 | F14: 外壁 Y6 より北の線分を実測
A15: AC-1（上段） | B15: 1.27 | C15: 0.9 | D15: 2.17
A16: AC-2（下段） | B16: 0.68 | C16: 2.2 | D16: 2.88
A17: RAC（上段） | B17: 1.21 | C17: 0.9 | D17: 2.11
A18: 合計 → 内訳書 | B18: 3.81 | C18: 6.2 | D18: 10.01 | F18: 10m
A20: 3. ドレン配管（空調設備図の口径ラベルで区分）
A21: 区間 | B21: 口径 | C21: 平面実測(m) | D21: 想定加算(m) | E21: 合計(m) | F21: 備考
A22: 主管 接続立上り〜西カセット合流 | B22: 40A | C22: 3.29 | D22: 2.45 | E22: 5.74 | F22: 天井内→H=150 立下り 2.45m
A23: 主管 西カセット合流〜AC-2合流 | B23: 30A | C23: 3.41 | D23: 0 | E23: 3.41
A24: 主管 AC-2合流〜東カセット | B24: 25A | C24: 2.72 | D24: 0.6 | E24: 3.32 | F24: 機器接続・ドレンアップ立上り
A25: AC-2 枝 | B25: 25A | C25: 1.28 | D25: 0.3 | E25: 1.58 | F25: ドレンアップ立上り
A26: 西カセット 枝 | B26: 25A | C26: 0.76 | D26: 0.3 | E26: 1.06 | F26: ドレンアップ立上り
A27: RAC | B27: 25A | C27: 0.44 | D27: 1.9 | E27: 2.34 | F27: 壁内 立下り（NDB-20-25 経由で接続）
A28: 合計 → 内訳書 | C28: 11.9 | D28: 5.55 | E28: 17.45 | F28: VP25 9m・VP30 4m・VP40 6m（保温も同長）
A30: 4. 機器台数（換気空調機器表・室外機設置概要図）
A31: 記号 | B31: 台数 | C31: 備考
A32: AC-1 天井カセット形 5馬力 SSRC140C | B32: 室内2・室外2 | C32: 客席。室外機は架台①の下段・上段
A33: AC-2 天井ビルトイン形 5馬力 SSRB140C | B33: 室内1・室外1 | C33: 厨房。室外機は架台②の下段。吹出しパンカー×4（支給）・ダクトは範囲外
A34: RAC ルームエアコン 2.2kW | B34: 室内1・室外1 | C34: 店長室。室外機は架台②の上段
A35: 鉄骨架台 2段積み | B35: 2基 | C35: 特記「空調本工事」。溶融亜鉛メッキ
A36: 外壁貫通 | B36: 4箇所 | C36: 冷媒管 4系統の外壁貫通位置（F-02-1）

Sheet 単価マスタ(内部)
A1: 単価マスタ（内部） 原価＝材料原価＋人工×労務原価日額、提出（定価ベース）＝原価×提出係数。参考列は宮地機工 参考見積8件（2025.11〜2026.10）から整理（三矢寮見積と共通）
A2: 労務原価日額 19,000 円/人工 参考見積の人工単価 23,225 円/人工（6330476-3 配管工費 40人工 929,000） 提出係数 1.22 材料係数 ×1.85（継手30%＋消耗15%＋支持金物40%）
A4: キー | B4: 材料原価 | C4: 人工 | D4: 労務原価 | E4: 原価 | F4: 提出(定価ベース) | G4: 参考定価ベース | H4: 当社/参考 | I4: 出典・根拠
A5: IN_CASSETTE | B5: 2000 | C5: 0.9 | D5: =ROUND(C5*LABOR_DAY,0) -> 17100 | E5: =IF(B5="","",B5+D5) -> 19100 | F5: =IF(E5="","",ROUND(E5*COEF,-1)) -> 23300 | G5: 21700 | H5: =IF(OR(G5="",F5=""),"",F5/G5) -> 1.0737327 | I5: 6330476-3 搬入据付 238,750/11台≒21,700/台。木造天井のため吊ボルト受け金物・吊ボルト4本分を材料に加算
A6: IN_BUILTIN | B6: 2500 | C6: 1.2 | D6: =ROUND(C6*LABOR_DAY,0) -> 22800 | E6: =IF(B6="","",B6+D6) -> 25300 | F6: =IF(E6="","",ROUND(E6*COEF,-1)) -> 30870 | G6: 27860 | H6: =IF(OR(G6="",F6=""),"",F6/G6) -> 1.1080402 | I6: 6330558 VRV 大形室内機 搬入据付 27,860/台 相当（ビルトイン 5HP 約50kg、吊ボルト・受け金物共）
A7: IN_RAC | B7: 500 | C7: 0.4 | D7: =ROUND(C7*LABOR_DAY,0) -> 7600 | E7: =IF(B7="","",B7+D7) -> 8100 | F7: =IF(E7="","",ROUND(E7*COEF,-1)) -> 9880 | I7: 6330539 RA 搬入据付 12,500/組（室内外1組）の室内機分（据付板・アンカー共）
A8: REF_3_20 | B8: 6700 | C8: 0.24 | D8: =ROUND(C8*LABOR_DAY,0) -> 4560 | E8: =IF(B8="","",B8+D8) -> 11260 | F8: =IF(E8="","",ROUND(E8*COEF,-1)) -> 13740 | G8: 12556 | H8: =IF(OR(G8="",F8=""),"",F8/G8) -> 1.0942975 | I8: 6330476-3 / 6330344-1 9.52+15.88 4,025/m・4.6 m/人工（10t×2）に、ガス管保温20t（耐熱PEF）の材料差 600/m・人工 0.02/m を加算
A9: REF_1_20 | B9: 2600 | C9: 0.22 | D9: =ROUND(C9*LABOR_DAY,0) -> 4180 | E9: =IF(B9="","",B9+D9) -> 6780 | F9: =IF(E9="","",ROUND(E9*COEF,-1)) -> 8270 | G9: 7328 | H9: =IF(OR(G9="",F9=""),"",F9/G9) -> 1.128548 | I9: 6330539 2分3分 1,450/m想定・5 m/人工 に、ガス管保温20t の材料差 400/m・人工 0.02/m を加算
A10: CASE_OUT | B10: 2200 | C10: 0.12 | D10: =ROUND(C10*LABOR_DAY,0) -> 2280 | E10: =IF(B10="","",B10+D10) -> 4480 | F10: =IF(E10="","",ROUND(E10*COEF,-1)) -> 5470 | G10: 3516 | H10: =IF(OR(G10="",F10=""),"",F10/G10) -> 1.5557452 | I10: 屋外用スリムダクト（耐候樹脂）本体＋ウォールコーナー・エルボ・端末カバー等の継手を m 当りに按分。参考は配管保温工事費 1,194/m（6330476-3）
A11: WALL_PEN | B11: 1500 | C11: 0.25 | D11: =ROUND(C11*LABOR_DAY,0) -> 4750 | E11: =IF(B11="","",B11+D11) -> 6250 | F11: =IF(E11="","",ROUND(E11*COEF,-1)) -> 7630 | I11: 外壁穴明け φ65〜75（木造・サイディング）・パテ埋め・シーリング（参考実績なし）
A12: LEAK_TEST | B12: 3000 | C12: 0.6 | D12: =ROUND(C12*LABOR_DAY,0) -> 11400 | E12: =IF(B12="","",B12+D12) -> 14400 | F12: =IF(E12="","",ROUND(E12*COEF,-1)) -> 17570 | G12: 20000 | H12: =IF(OR(G12="",F12=""),"",F12/G12) -> 0.8785 | I12: 気密テスト 15,000〜25,000/系統・真空引き 3,750〜5,640/系統（6330558/344-1/549）
A13: LEAK_TEST_RAC | B13: 1500 | C13: 0.3 | D13: =ROUND(C13*LABOR_DAY,0) -> 5700 | E13: =IF(B13="","",B13+D13) -> 7200 | F13: =IF(E13="","",ROUND(E13*COEF,-1)) -> 8780 | G13: 7500 | H13: =IF(OR(G13="",F13=""),"",F13/G13) -> 1.1706667 | I13: RA 気密・真空引き（6330539 試運転 7,500/3台 等から想定）
A14: VP25 | B14: 475 | C14: 0.11 | D14: =ROUND(C14*LABOR_DAY,0) -> 2090 | E14: =IF(B14="","",B14+D14) -> 2565 | F14: =IF(E14="","",ROUND(E14*COEF,-1)) -> 3130 | G14: 3134 | H14: =IF(OR(G14="",F14=""),"",F14/G14) -> 0.99872368 | I14: 6330344-1/476-3/248-2 VP25 313/m、工費 2,497/m
A15: VP30 | B15: 620 | C15: 0.12 | D15: =ROUND(C15*LABOR_DAY,0) -> 2280 | E15: =IF(B15="","",B15+D15) -> 2900 | F15: =IF(E15="","",ROUND(E15*COEF,-1)) -> 3540 | I15: VP25・VP40 の補間
A16: VP40 | B16: 760 | C16: 0.13 | D16: =ROUND(C16*LABOR_DAY,0) -> 2470 | E16: =IF(B16="","",B16+D16) -> 3230 | F16: =IF(E16="","",ROUND(E16*COEF,-1)) -> 3940 | I16: VP25 比例
A17: CHECK_VALVE | B17: 2800 | C17: 0.1 | D17: =ROUND(C17*LABOR_DAY,0) -> 1900 | E17: =IF(B17="","",B17+D17) -> 4700 | F17: =IF(E17="","",ROUND(E17*COEF,-1)) -> 5730 | I17: ドレンホース用逆止弁 NDB-20-25（図示品番）材＋取付（市況）
A18: WATER_TEST | B18: 0 | C18: 0.25 | D18: =ROUND(C18*LABOR_DAY,0) -> 4750 | E18: =IF(B18="","",B18+D18) -> 4750 | F18: =IF(E18="","",ROUND(E18*COEF,-1)) -> 5800 | I18: ドレン通水試験（0.25人工）
A19: DI_25 | B19: 900 | C19: 0.06 | D19: =ROUND(C19*LABOR_DAY,0) -> 1140 | E19: =IF(B19="","",B19+D19) -> 2040 | F19: =IF(E19="","",ROUND(E19*COEF,-1)) -> 2490 | I19: GW保温筒20 ALGC 25A（参考実績なし・市況）
A20: DI_30 | B20: 1000 | C20: 0.065 | D20: =ROUND(C20*LABOR_DAY,0) -> 1235 | E20: =IF(B20="","",B20+D20) -> 2235 | F20: =IF(E20="","",ROUND(E20*COEF,-1)) -> 2730 | I20: GW保温筒20 ALGC 30A（同上）
A21: DI_40 | B21: 1100 | C21: 0.07 | D21: =ROUND(C21*LABOR_DAY,0) -> 1330 | E21: =IF(B21="","",B21+D21) -> 2430 | F21: =IF(E21="","",ROUND(E21*COEF,-1)) -> 2960 | I21: GW保温筒20 ALGC 40A（同上）
A22: OUT_LOW | B22: 1500 | C22: 0.8 | D22: =ROUND(C22*LABOR_DAY,0) -> 15200 | E22: =IF(B22="","",B22+D22) -> 16700 | F22: =IF(E22="","",ROUND(E22*COEF,-1)) -> 20370 | G22: 21700 | H22: =IF(OR(G22="",F22=""),"",F22/G22) -> 0.93870968 | I22: 6330476-3 搬入据付 21,700/台（基礎・架台は別行）。防振ゴム取付・系統名表示共
A23: OUT_UP | B23: 1500 | C23: 1.3 | D23: =ROUND(C23*LABOR_DAY,0) -> 24700 | E23: =IF(B23="","",B23+D23) -> 26200 | F23: =IF(E23="","",ROUND(E23*COEF,-1)) -> 31960 | G23: 21700 | H23: =IF(OR(G23="",F23=""),"",F23/G23) -> 1.4728111 | I23: 架台上段（H≒1.6m）への揚重（人力3名＋リフター）を人工に加算
A24: OUT_RAC | B24: 500 | C24: 0.5 | D24: =ROUND(C24*LABOR_DAY,0) -> 9500 | E24: =IF(B24="","",B24+D24) -> 10000 | F24: =IF(E24="","",ROUND(E24*COEF,-1)) -> 12200 | I24: 6330539 RA 搬入据付 12,500/組（室内外1組）の室外機分＋架台上段への揚重
A25: FRAME_PP | B25: 130000 | C25: 1 | D25: =ROUND(C25*LABOR_DAY,0) -> 19000 | E25: =IF(B25="","",B25+D25) -> 149000 | F25: =IF(E25="","",ROUND(E25*COEF,-1)) -> 181780 | I25: 鉄骨2段架台 溶融亜鉛メッキ 5HP×2用（ダイキン H1,430 対応の段間寸法）材＋組立・据付。既製品相当の想定（要メーカー見積）
A26: FRAME_PR | B26: 110000 | C26: 1 | D26: =ROUND(C26*LABOR_DAY,0) -> 19000 | E26: =IF(B26="","",B26+D26) -> 129000 | F26: =IF(E26="","",ROUND(E26*COEF,-1)) -> 157380 | I26: 鉄骨2段架台 溶融亜鉛メッキ 5HP＋RA用 材＋組立・据付。既製品相当の想定（要メーカー見積）
A27: FRAME_BASE | B27: 15000 | C27: 0.5 | D27: =ROUND(C27*LABOR_DAY,0) -> 9500 | E27: =IF(B27="","",B27+D27) -> 24500 | F27: =IF(E27="","",ROUND(E27*COEF,-1)) -> 29890 | G27: 23200 | H27: =IF(OR(G27="",F27=""),"",F27/G27) -> 1.2883621 | I27: コンクリート置基礎 4個/基＋ステンレスアンカー。参考 基礎工事 5,800〜10,000/台（6330539/549/476-3）
A28: VIB | B28: 2500 | C28: 0.1 | D28: =ROUND(C28*LABOR_DAY,0) -> 1900 | E28: =IF(B28="","",B28+D28) -> 4400 | F28: =IF(E28="","",ROUND(E28*COEF,-1)) -> 5370 | I28: 室外機用防振ゴム 4個/台（市況）
A30: 参考見積の経費構造
A31: 部門内経費 | B31: 消耗品及び雑材料 2.6%＋資材運搬交通費 3.5%＋現場経費 7.4% ＝ 15.7%（据付・撤去）／ 3.0%＋4.1%＋8.6% ＝ 19.0%（配管・ダクト・電気）
A32: 工事諸経費 | B32: 直接工事費の 5.0%
A33: 出精値引 | B33: 参考見積 8件で 9.9〜35.1%（提出額の丸め）
A34: 法定福利費 | B34: 労務費×16.04%（参考見積は金額内含で注記）。当社は別項目で 16.375%（令和8年度）
A35: 据付単価 | B35: 搬入据付 21,700/台（6330476-3）・27,860/台（6330558 VRV）・12,500/組（6330539 RA）
A36: 配管 | B36: 冷媒 9.52+15.88 4,025/m（10t×2）、ペアコイル 6.35+9.52 988、VP25 313/m、配管工費 4.6〜5 m/人工（冷媒）・9〜12 m/人工（塩ビ）
A37: その他 | B37: 気密 15,000〜25,000、真空引き 3,750〜5,640、基礎工事 5,800〜10,000/台
